texlite/__init__.py
texlite/__main__.py
texlite/_version.py
texlite/cli.py
texlite/compile.py
texlite/io.py
texlite/messages.py
texlite/parse.py
texlite/utils.py
texlite/components/__init__.py
texlite/components/common.py
texlite/components/equation.py
texlite/components/figure.py
texlite/components/list.py
texlite/components/meta.py
texlite/components/section.py
texlite/components/text.py
texlite-1.2.1.dist-info/LICENSE
texlite-1.2.1.dist-info/METADATA
texlite-1.2.1.dist-info/WHEEL
texlite-1.2.1.dist-info/entry_points.txt
texlite-1.2.1.dist-info/top_level.txt
texlite-1.2.1.dist-info/RECORD
