Metadata-Version: 2.1
Name: texlite
Version: 1.2.1
Summary: A lightweight, open-source tool for writing standard LaTeX documents cleanly using Markdown-style syntax.
Home-page: https://github.com/lucrae/texlite
Author: Lucien Rae Gentil
Author-email: lucienraegentil@gmail.com
License: UNKNOWN
Platform: UNKNOWN
Classifier: Programming Language :: Python :: 3
Classifier: Programming Language :: Python :: 3.6
Classifier: Programming Language :: Python :: 3.7
Classifier: Programming Language :: Python :: 3.8
Classifier: License :: OSI Approved :: GNU General Public License v3 (GPLv3)
Classifier: Operating System :: OS Independent
Requires-Python: >=3.6
